cli/__init__.py
cli/main.py
paidiverpy/__init__.py
paidiverpy/configuration-schema.json
paidiverpy/images_layer.py
paidiverpy/paidiverpy.py
paidiverpy/colour_layer/__init__.py
paidiverpy/colour_layer/colour_layer.py
paidiverpy/config/__init__.py
paidiverpy/config/config_params.py
paidiverpy/config/configuration.py
paidiverpy/convert_layer/__init__.py
paidiverpy/convert_layer/convert_layer.py
paidiverpy/custom_layer/__init__.py
paidiverpy/custom_layer/_custom_algorithm_example.py
paidiverpy/custom_layer/_custom_algorithm_example_dataset.py
paidiverpy/custom_layer/custom_layer.py
paidiverpy/frontend/__init__.py
paidiverpy/frontend/app.py
paidiverpy/frontend/json_dump.py
paidiverpy/frontend/parse.py
paidiverpy/frontend/render.py
paidiverpy/frontend/widgets/__init__.py
paidiverpy/frontend/widgets/app.py
paidiverpy/frontend/widgets/config_general.py
paidiverpy/frontend/widgets/utils.py
paidiverpy/investigation_layer/__init__.py
paidiverpy/investigation_layer/investigation_layer.py
paidiverpy/metadata_parser/__init__.py
paidiverpy/metadata_parser/ifdo_tools.py
paidiverpy/metadata_parser/metadata_conventions.json
paidiverpy/metadata_parser/metadata_parser.py
paidiverpy/models/__init__.py
paidiverpy/models/client_params.py
paidiverpy/models/colour_params.py
paidiverpy/models/config_model.py
paidiverpy/models/convert_params.py
paidiverpy/models/custom_params.py
paidiverpy/models/general_config.py
paidiverpy/models/open_params.py
paidiverpy/models/position_params.py
paidiverpy/models/sampling_params.py
paidiverpy/models/step_config.py
paidiverpy/open_layer/__init__.py
paidiverpy/open_layer/open_layer.py
paidiverpy/open_layer/utils.py
paidiverpy/pipeline/__init__.py
paidiverpy/pipeline/pipeline.py
paidiverpy/pipeline/pipeline_params.py
paidiverpy/position_layer/__init__.py
paidiverpy/position_layer/position_layer.py
paidiverpy/sampling_layer/__init__.py
paidiverpy/sampling_layer/sampling_layer.py
paidiverpy/utils/__init__.py
paidiverpy/utils/base_model.py
paidiverpy-0.2.1.dist-info/licenses/LICENSE
paidiverpy-0.2.1.dist-info/METADATA
paidiverpy-0.2.1.dist-info/WHEEL
paidiverpy-0.2.1.dist-info/entry_points.txt
paidiverpy-0.2.1.dist-info/top_level.txt
paidiverpy-0.2.1.dist-info/RECORD
