Metadata-Version: 2.4
Name: Paidiverpy
Version: 0.2.1
Summary: A library to preprocess image data.
Author-email: Tobias Ferreira <tobias.ferreira@noc.ac.uk>, Mojtaba Masoudi <mojtaba.masoudi@noc.ac.uk>, Van Loïc Audenhaege <loic.audenhaege@noc.ac.uk>, Erik Orenstein <erik.orenstein@noc.ac.uk>, Colin Sauze <colin.sauze@noc.ac.uk>, Jennifer Durden <jennifer.durden@noc.ac.uk>
Maintainer-email: Tobias Ferreira <tobias.ferreira@noc.ac.uk>
License:                                  Apache License
Project-URL: Repository, https://github.com/paidiver/paidiverpy
Project-URL: Issues, https://github.com/paidiver/paidiverpy/issues
Project-URL: Changelog, https://github.com/paidiver/paidiverpy/CHANGELOG.md
Project-URL: ReadTheDocs, https://paidiverpy.readthedocs.io
Keywords: data,paidiver,noc
Classifier: Programming Language :: Python :: 3
Classifier: Intended Audience :: Science/Research
Requires-Python: >=3.10
License-File: LICENSE
Requires-Dist: pandas>=2.2.2
Requires-Dist: pillow>=10.4.0
Requires-Dist: scikit-image>=0.24.0
Requires-Dist: scipy>=1.14
Requires-Dist: tqdm>=4.66.4
Requires-Dist: PyYAML>=6.0
Requires-Dist: openpyxl>=3.1
Requires-Dist: shapely==2.0.7
Requires-Dist: geopy>=2.4.1
Requires-Dist: geopandas>=1.0.1
Requires-Dist: dask-image==2024.5.3
Requires-Dist: dask>=2024.10.0
Requires-Dist: distributed>=2024.10.0
Requires-Dist: jsonschema>=4.23.0
Requires-Dist: matplotlib>=3.5.0
Requires-Dist: ipython>=8.26.0
Requires-Dist: dask-jobqueue>=0.9.0
Requires-Dist: python-dotenv>=1.0.1
Requires-Dist: boto3>=1.35.92
Requires-Dist: botocore>=1.35.92
Requires-Dist: opencv-python>=4.11
Requires-Dist: rawpy>=0.24.0
Requires-Dist: pydantic>=2.9.2
Requires-Dist: requests>=2.25.1
Requires-Dist: xarray>=2024.12.0
Provides-Extra: dev
Requires-Dist: build; extra == "dev"
Requires-Dist: bump-my-version; extra == "dev"
Requires-Dist: coverage[toml]; extra == "dev"
Requires-Dist: pytest; extra == "dev"
Requires-Dist: pytest-cov; extra == "dev"
Requires-Dist: ruff==0.9.5; extra == "dev"
Requires-Dist: sphinx; extra == "dev"
Requires-Dist: sphinx_rtd_theme; extra == "dev"
Requires-Dist: sphinx-autoapi; extra == "dev"
Requires-Dist: myst_parser; extra == "dev"
Requires-Dist: plotly; extra == "dev"
Provides-Extra: docs
Requires-Dist: sphinx; extra == "docs"
Requires-Dist: sphinx_rtd_theme; extra == "docs"
Requires-Dist: sphinx__theme; extra == "docs"
Requires-Dist: sphinx-autoapi; extra == "docs"
Requires-Dist: sphinx-copybutton; extra == "docs"
Requires-Dist: sphinx-book-theme; extra == "docs"
Requires-Dist: myst_parser; extra == "docs"
Requires-Dist: nbsphinx; extra == "docs"
Requires-Dist: numpydoc; extra == "docs"
Requires-Dist: sphinx-last-updated-by-git; extra == "docs"
Requires-Dist: sphinx-codeautolink; extra == "docs"
Requires-Dist: sphinx_design; extra == "docs"
Requires-Dist: pickleshare; extra == "docs"
Provides-Extra: publishing
Requires-Dist: build; extra == "publishing"
Requires-Dist: twine; extra == "publishing"
Requires-Dist: wheel; extra == "publishing"
Provides-Extra: test
Requires-Dist: pytest>=7.2.0; extra == "test"
Requires-Dist: pytest-cov; extra == "test"
Dynamic: license-file
